{
    "title": "Restrictions (macOS) (com.apple.applicationaccess)",
    "description": "macOS Restrictions preferences",
    "properties": {
        "allowPasswordAutoFill": {
            "type": "boolean",
            "title": "Allow password AutoFill",
            "default": true,
            "property_order": 5
        },
        "allowAutoUnlock": {
            "type": "boolean",
            "title": "Allow Apple Watch to auto unlock device",
            "default": true,
            "property_order": 10
        },
        "allowCamera": {
            "type": "boolean",
            "title": "Allow Camera",
            "default": true,
            "property_order": 15
        },
        "allowContentCaching": {
            "type": "boolean",
            "title": "Allow Content Caching",
            "default": true,
            "property_order": 20
        },
        "allowiTunesFileSharing": {
            "type": "boolean",
            "title": "Allow iTunes File Sharing",
            "default": true,
            "property_order": 25
        },
        "allowActivityContinuation": {
            "type": "boolean",
            "title": "Allow Handoff",
            "default": true,
            "property_order": 30
        },
        "allowMusicService": {
            "type": "boolean",
            "title": "Allow Apple Music",
            "default": true,
            "property_order": 35
        },
        "allowCloudBTMM": {
            "type": "boolean",
            "title": "Allow iCloud Back to My Mac",
            "default": true,
            "property_order": 40
        },
        "allowCloudBookmarks": {
            "type": "boolean",
            "title": "Allow iCloud Bookmarks",
            "default": true,
            "property_order": 45
        },
        "allowCloudCalendar": {
            "type": "boolean",
            "title": "Allow iCloud Calendar",
            "default": true,
            "property_order": 50
        },
        "allowCloudAddressBook": {
            "type": "boolean",
            "title": "Allow iCloud Contacts",
            "default": true,
            "property_order": 55
        },
        "allowCloudDocumentSync": {
            "type": "boolean",
            "title": "Allow iCloud Drive",
            "default": true,
            "property_order": 60
        },
        "allowCloudDesktopAndDocuments": {
            "type": "boolean",
            "title": "Allow iCloud Desktop & Documents",
            "default": true,
            "property_order": 65
        },
        "allowCloudFMM": {
            "type": "boolean",
            "title": "Allow iCloud Find My Mac",
            "default": true,
            "property_order": 70
        },
        "allowCloudKeychainSync": {
            "type": "boolean",
            "title": "Allow iCloud Keychain",
            "default": true,
            "property_order": 75
        },
        "allowCloudMail": {
            "type": "boolean",
            "title": "Allow iCloud Mail",
            "default": true,
            "property_order": 80
        },
        "allowCloudNotes": {
            "type": "boolean",
            "title": "Allow iCloud Notes",
            "default": true,
            "property_order": 85
        },
        "allowCloudPhotoLibrary": {
            "type": "boolean",
            "title": "Allow iCloud Photo Library",
            "default": true,
            "property_order": 90
        },
        "allowCloudReminders": {
            "type": "boolean",
            "title": "Allow iCloud Reminders",
            "default": true,
            "property_order": 95
        },
        "allowSpotlightInternetResults": {
            "type": "boolean",
            "title": "Allow Siri Suggestions",
            "default": true,
            "property_order": 100
        },
        "allowFingerprintForUnlock": {
            "type": "boolean",
            "title": "Allow Touch ID / Face ID to unlock device",
            "default": true,
            "property_order": 105
        },
        "allowDefinitionLookup": {
            "type": "boolean",
            "title": "Allow definition lookup",
            "default": true,
            "property_order": 110
        },
        "allowDeprecatedWebKitTLS": {
            "type": "boolean",
            "title": "Allow accessing websites using TLS 1.0 and 1.1",
            "default": false,
            "description": "Allow websites that use TLS 1.0 and TLS 1.1 to be accessed using Safari.",
            "links": [
                {
                    "rel": "More information",
                    "href": "https://docs.jamf.com/10.20.0/jamf-pro/release-notes/What%27s_New.html"
                }
            ],
            "property_order": 115
        },
        "allowFindMyDevice": {
            "type": "boolean",
            "title": "Allow Find My Devices",
            "default": true,
            "property_order": 120
        },
        "allowFindMyFriends": {
            "type": "boolean",
            "title": "Allow Find My Friends",
            "default": true,
            "property_order": 125
        },
        "allowPasswordSharing": {
            "type": "boolean",
            "title": "Allow password sharing",
            "default": true,
            "property_order": 130
        },
        "allowAirPrintiBeaconDiscovery": {
            "type": "boolean",
            "title": "Allow discovery of AirPrint printers using iBeacons",
            "default": true,
            "property_order": 135
        },
        "forceAirPrintTrustedTLSRequirement": {
            "type": "boolean",
            "title": "Disallow AirPrint to destinations with untrusted certificates",
            "default": false,
            "property_order": 140
        },
        "allowScreenShot": {
            "type": "boolean",
            "title": "Allow screenshots and screen recording",
            "default": true,
            "links": [
                {
                    "rel": "More information",
                    "href": "https://developer.apple.com/documentation/devicemanagement/restrictions"
                }
            ],
            "property_order": 145
        },
        "allowRemoteScreenObservation": {
            "type": "boolean",
            "title": "Allow AirPlay and View Screen by Classroom app",
            "default": true,
            "description": "If 'Allow Screenshots and Screen Recording' is set to 'false', it also overrides this preference and prevents the Classroom app from observing remote screens.",
            "links": [
                {
                    "rel": "More information",
                    "href": "https://developer.apple.com/documentation/devicemanagement/restrictions"
                }
            ],
            "property_order": 150
        },
        "forceClassroomUnpromptedScreenObservation": {
            "type": "boolean",
            "title": "Allow Classroom app to perform AirPlay and View Screen without prompting",
            "default": false,
            "description": "If Allow screenshots and screen recording is set to 'false' or Allow AirPlay and View Screen by Classroom app, they also override this preference and prevents the Classroom app from unprompted remote AirPlay and view screens.\n\nAdditionally, if set to true and ScreenObservationPermissionModificationAllowed is also true in the Education payload, a student enrolled in a managed course via the Classroom app will automatically give permission to that course's teacher's requests to observe the student's screen without prompting the student.",
            "property_order": 155
        },
        "forceClassroomUnpromptedAppAndDeviceLock": {
            "type": "boolean",
            "title": "Allow Classroom to lock apps or the device without prompting",
            "default": false,
            "property_order": 160
        },
        "forceClassroomAutomaticallyJoinClasses": {
            "type": "boolean",
            "title": "Automatically join Classroom classes without prompting",
            "default": false,
            "property_order": 165
        },
        "forceClassroomRequestPermissionToLeaveClasses": {
            "type": "boolean",
            "title": "Require teacher permission to leave Classroom app unmanaged classes",
            "default": false,
            "property_order": 170
        },
        "allowPasswordProximityRequests": {
            "type": "boolean",
            "title": "Allow proximity based password sharing requests",
            "default": true,
            "property_order": 175
        },
        "forceDelayedSoftwareUpdates": {
            "type": "boolean",
            "title": "Defer OS Software Updates",
            "default": false,
            "property_order": 180
        },
        "forceDelayedAppSoftwareUpdates": {
            "type": "boolean",
            "title": "Defer non-OS Software Updates",
            "default": false,
            "description": "If true, delays user visibility of non-OS Software Updates. Requires a supervised device.",
            "property_order": 185
        },
        "enforcedSoftwareUpdateDelay": {
            "type": "integer",
            "title": "Deferred Software Updates Delay",
            "default": 30,
            "description": "Number of days the software updates will be hidden from the user.",
            "property_order": 190
        }
    }
}