{
    "title": "NoMAD Login+ (menu.nomad.login.okta)",
    "description": "NoMAD Login+ settings",
    "properties": {
        "AuthServer": {
            "type": "string",
            "property_order": 5
        },
        "DenyLocal": {
            "type": "boolean",
            "property_order": 10
        },
        "DenyLocalExcluded": {
            "type": "array",
            "items": {
                "type": "string",
                "title": "Username"
            },
            "property_order": 15
        },
        "LocalFallback": {
            "type": "boolean",
            "property_order": 20
        },
        "Migrate": {
            "type": "boolean",
            "property_order": 25
        },
        "MigrateUsersHide": {
            "type": "array",
            "items": {
                "type": "string",
                "title": "Username"
            },
            "property_order": 30
        },
        "LoginLogo": {
            "type": "string",
            "property_order": 35
        },
        "BackgroundImage": {
            "type": "string",
            "property_order": 40
        },
        "HelpURL": {
            "type": "string",
            "property_order": 45
        },
        "OIDCAccessClientID": {
            "type": "string",
            "property_order": 50
        },
        "OIDCAdminClientID": {
            "type": "string",
            "property_order": 55
        },
        "OIDCAuthServer": {
            "type": "string",
            "property_order": 60
        },
        "OIDCRedirectURI": {
            "type": "string",
            "default": "nomadoauth://oauth-callback/okta",
            "property_order": 65
        },
        "OIDCSecondaryLoginClientID": {
            "type": "string",
            "property_order": 70
        },
        "CreateAdminUser": {
            "type": "boolean",
            "property_order": 75
        },
        "EnableFDE": {
            "type": "boolean",
            "property_order": 80
        },
        "EnableFDERecoveryKey": {
            "type": "boolean",
            "property_order": 85
        },
        "EnableFDERecoveryKeyPath": {
            "type": "string",
            "property_order": 90
        },
        "LAPSUser": {
            "type": "string",
            "property_order": 95
        },
        "ScriptPath": {
            "type": "string",
            "property_order": 100
        },
        "ScriptArgs": {
            "type": "array",
            "items": {
                "type": "string",
                "title": "Arguments"
            },
            "property_order": 105
        },
        "DemobilizeUsers": {
            "type": "boolean",
            "property_order": 110
        }
    }
}